docs/dev/README.md
docs/dev/github.md
docs/dev/pypi.md
docs/dev/tofu_ui.md
examples/security/makefile
examples/security/pyproject.toml
examples/security/scanner.py
examples/security/module/main.tf
tests/__init__.py
tests/conftest.py
tests/test_apply.py
tests/test_destroy.py
tests/test_exception.py
tests/test_init.py
tests/test_output.py
tests/test_plan.py
tests/test_state.py
tests/test_validate.py
tests/test_version.py
tests/module/main.tf
tests/module_error/main.tf
tofupy/__init__.py
tofupy/_version.py
tofupy/py.typed
tofupy/schema.py
tofupy/tofu.py
tofupy-1.1.2.dist-info/licenses/LICENSE
tofupy-1.1.2.dist-info/METADATA
tofupy-1.1.2.dist-info/WHEEL
tofupy-1.1.2.dist-info/top_level.txt
tofupy-1.1.2.dist-info/RECORD
